iso_freeze/__init__.py
iso_freeze/iso_freeze.py
iso_freeze-0.0.9.post2.dist-info/METADATA
iso_freeze-0.0.9.post2.dist-info/WHEEL
iso_freeze-0.0.9.post2.dist-info/entry_points.txt
iso_freeze-0.0.9.post2.dist-info/licenses/LICENSE
iso_freeze-0.0.9.post2.dist-info/RECORD
