Metadata-Version: 2.1
Name: iso-freeze
Version: 0.0.9.post2
Summary: Use pip install --report to generate pinned requirements for different optional dependencies.
Project-URL: Homepage, https://github.com/sbaack/iso-freeze
Project-URL: Bug Tracker, https://github.com/sbaack/iso-freeze/issues
Author: Stefan Baack
License: MIT License
Classifier: License :: OSI Approved :: MIT License
Classifier: Operating System :: OS Independent
Classifier: Programming Language :: Python :: 3
Requires-Python: >=3.9
Requires-Dist: tomli>=1.1.0; python_version < '3.11'
Provides-Extra: dev
Requires-Dist: pytest; extra == 'dev'
Requires-Dist: pytest-mock; extra == 'dev'
